MANIFEST.in
README.md
requirements.txt
setup.cfg
setup.py
tests/conftest.py
tests/test_client.py
tests/test_component_api.py
tests/test_constants.py
tests/test_create_reply.py
tests/test_crypto.py
tests/test_deserialize_reply.py
tests/test_enterprise_client.py
tests/test_enterprise_create_reply.py
tests/test_enterprise_parser.py
tests/test_events.py
tests/test_fields.py
tests/test_messages.py
tests/test_oauth.py
tests/test_parser.py
tests/test_pay.py
tests/test_payment.py
tests/test_replies.py
tests/test_send_messages.py
tests/test_session.py
tests/test_utils.py
tests/certs/rsa_private_key.pem
tests/certs/rsa_public_key.pem
tests/fixtures/bizwifi_device_add.json
tests/fixtures/bizwifi_device_delete.json
tests/fixtures/bizwifi_device_list.json
tests/fixtures/bizwifi_homepage_get.json
tests/fixtures/bizwifi_homepage_set.json
tests/fixtures/bizwifi_qrcode_get.json
tests/fixtures/bizwifi_shop_get.json
tests/fixtures/bizwifi_shop_list.json
tests/fixtures/bizwifi_statistics_list.json
tests/fixtures/changeopenid.json
tests/fixtures/customservice_getkflist.json
tests/fixtures/customservice_getonlinekflist.json
tests/fixtures/customservice_kfaccount_add.json
tests/fixtures/customservice_kfaccount_del.json
tests/fixtures/customservice_kfaccount_update.json
tests/fixtures/customservice_kfaccount_uploadheadimg.json
tests/fixtures/customservice_kfsession_close.json
tests/fixtures/customservice_kfsession_create.json
tests/fixtures/customservice_kfsession_getsession.json
tests/fixtures/customservice_kfsession_getsessionlist.json
tests/fixtures/customservice_kfsession_getwaitcase.json
tests/fixtures/customservice_msgrecord_getmsglist.json
tests/fixtures/datacube_getarticlesummary.json
tests/fixtures/datacube_getarticletotal.json
tests/fixtures/datacube_getinterfacesummary.json
tests/fixtures/datacube_getinterfacesummaryhour.json
tests/fixtures/datacube_getupstreammsg.json
tests/fixtures/datacube_getupstreammsgdist.json
tests/fixtures/datacube_getupstreammsgdistmonth.json
weixinpy.egg-info/PKG-INFO
weixinpy.egg-info/SOURCES.txt
weixinpy.egg-info/dependency_links.txt
weixinpy.egg-info/requires.txt
weixinpy.egg-info/top_level.txt